dykstra/Dykstra.py
dykstra/__init__.py
dykstra/version.py
Dykstra-0.0.0.dist-info/LICENSE
Dykstra-0.0.0.dist-info/METADATA
Dykstra-0.0.0.dist-info/WHEEL
Dykstra-0.0.0.dist-info/top_level.txt
Dykstra-0.0.0.dist-info/zip-safe
Dykstra-0.0.0.dist-info/RECORD
