Metadata-Version: 2.1
Name: Dykstra
Version: 0.0.0
Summary: An implementation of Dykstra's projection algorithm with robust stopping criteria.
Home-page: https://github.com/mjhough/Dykstra/
Author: Matthew Hough
Author-email: matt@hough.tv
License: MIT
Download-URL: https://github.com/numericalalgorithmsgroup/Dykstra/archive/v0.0.0.tar.gz
Keywords: mathematics optimization projection Dykstra
Platform: UNKNOWN
Classifier: Development Status :: 5 - Production/Stable
Classifier: Environment :: Console
Classifier: Framework :: IPython
Classifier: Framework :: Jupyter
Classifier: Intended Audience :: Science/Research
Classifier: License :: OSI Approved :: MIT License
Classifier: Operating System :: MacOS
Classifier: Operating System :: Microsoft :: Windows
Classifier: Operating System :: POSIX
Classifier: Operating System :: Unix
Classifier: Programming Language :: Python
Classifier: Programming Language :: Python :: 2
Classifier: Programming Language :: Python :: 3
Classifier: Topic :: Scientific/Engineering
Classifier: Topic :: Scientific/Engineering :: Mathematics
Requires-Dist: numpy (>=1.11)
